[
    {
      "quote": "Take care of your body. It's the only place you have to live.",
      "author": "Jim Rohn",
      "year": 1981,
      "location": "Unknown"
    },
    {
      "quote": "To keep the body in good health is a duty… otherwise we shall not be able to keep our mind strong and clear.",
      "author": "Buddha",
      "year": -500,
      "location": "India"
    },
    {
      "quote": "Wellness encompasses a healthy body, a sound mind, and a tranquil spirit. Enjoy the journey as you strive for wellness.",
      "author": "Laurette Gagnon Beaulieu",
      "year": 2001,
      "location": "Canada"
    },
    {
      "quote": "A healthy outside starts from the inside.",
      "author": "Robert Urich",
      "year": 2000,
      "location": "United States"
    },
    {
      "quote": "Health is a state of body. Wellness is a state of being.",
      "author": "J. Stanford",
      "year": 1998,
      "location": "Unknown"
    },
    {
      "quote": "Self-care is not a luxury. It is a necessity.",
      "author": "Audre Lorde",
      "year": 1988,
      "location": "United States"
    },
    {
      "quote": "The greatest wealth is health.",
      "author": "Virgil",
      "year": -30,
      "location": "Rome, Italy"
    },
    {
      "quote": "The mind and body are not separate. What affects one, affects the other.",
      "author": "Unknown",
      "year": 2020,
      "location": "Unknown"
    },
    {
      "quote": "Wellness is the complete integration of body, mind, and spirit – the realization that everything we do, think, feel, and believe has an effect on our state of well-being.",
      "author": "Greg Anderson",
      "year": 1997,
      "location": "United States"
    },
    {
      "quote": "The first wealth is health.",
      "author": "Ralph Waldo Emerson",
      "year": 1860,
      "location": "United States"
    }
  ]
  